aenigma/__init__.py
aenigma/analyzer.py
aenigma-0.1.1.dist-info/LICENSE
aenigma-0.1.1.dist-info/WHEEL
aenigma-0.1.1.dist-info/METADATA
aenigma-0.1.1.dist-info/RECORD
